minigpt-0.1.0.dist-info/METADATA
minigpt-0.1.0.dist-info/WHEEL
minigpt-0.1.0.dist-info/entry_points.txt
minigpt/__init__.py
minigpt/__main__.py
minigpt-0.1.0.dist-info/RECORD
